octmnist_classifier/__init__.py
octmnist_classifier/cli.py
octmnist_classifier/model.py
octmnist_classifier/predict.py
octmnist_classifier/preprocess.py
octmnist_classifier/utils.py
octmnist_classifier-0.1.2.dist-info/licenses/LICENSE
octmnist_classifier-0.1.2.dist-info/METADATA
octmnist_classifier-0.1.2.dist-info/WHEEL
octmnist_classifier-0.1.2.dist-info/entry_points.txt
octmnist_classifier-0.1.2.dist-info/top_level.txt
octmnist_classifier-0.1.2.dist-info/RECORD
